{
    "/js/admin/app.js": "/js/admin/app.js?id=c56a283014cc69764973",
    "/js/admin/app.js.map": "/js/admin/app.js.map?id=52a03000cc20ae971950",
    "/js/app.js": "/js/app.js?id=cb049404fe7ec78d78ef",
    "/css/app.css": "/css/app.css?id=1c2c48c92825e8749163",
    "/css/admin/app.css": "/css/admin/app.css?id=5609f55cf2cfc10adb70",
    "/js/app.js.map": "/js/app.js.map?id=6af1b495610bb248d5b6",
    "/css/app.css.map": "/css/app.css.map?id=2603b8e362f0422fd8a7",
    "/css/admin/app.css.map": "/css/admin/app.css.map?id=53b148777521c29687c6"
}
